filters_iso/__init__.py
phx_filters_iso-3.1.0.dist-info/LICENCE.txt
phx_filters_iso-3.1.0.dist-info/METADATA
phx_filters_iso-3.1.0.dist-info/WHEEL
phx_filters_iso-3.1.0.dist-info/entry_points.txt
phx_filters_iso-3.1.0.dist-info/top_level.txt
phx_filters_iso-3.1.0.dist-info/RECORD
