Metadata-Version: 2.1
Name: phx-filters-iso
Version: 3.1.0
Summary: Extends phx-filters, adding filters for interpreting ISO codes.
Author-email: Phoenix Zerin <phx@phx.nz>
License: MIT License
Project-URL: Documentation, https://filters.readthedocs.io/en/latest/extension_filters.html#iso-filters
Project-URL: Changelog, https://github.com/todofixthis/filters-iso/releases
Project-URL: Issues, https://github.com/todofixthis/filters-iso/issues
Project-URL: Repository, https://github.com/todofixthis/filters-iso
Keywords: bcp 47,data validation,i18n,ietf language tags,internationalisation,internationalization,iso,iso-3166,iso-4217,l10n,localisation,localization,standards
Classifier: Development Status :: 5 - Production/Stable
Classifier: Intended Audience :: Developers
Classifier: License :: OSI Approved :: MIT License
Classifier: Programming Language :: Python :: 3
Classifier: Programming Language :: Python :: 3.12
Classifier: Programming Language :: Python :: 3.11
Classifier: Programming Language :: Python :: 3.10
Classifier: Topic :: Software Development :: Libraries :: Python Modules
Classifier: Topic :: Text Processing :: Filters
Requires-Python: >=3.10
License-File: LICENCE.txt
Requires-Dist: phx-filters >=3.4.0
Requires-Dist: iso3166
Requires-Dist: language-tags
Requires-Dist: py-moneyed
Provides-Extra: build-system
Requires-Dist: build ; extra == 'build-system'
Requires-Dist: twine ; extra == 'build-system'
Provides-Extra: test-runner
Requires-Dist: tox ; extra == 'test-runner'
